dtwsa/__init__.py
dtwsa/dtwsa.py
dtwsa/metrics.py
dtwsa-0.1.0.dist-info/METADATA
dtwsa-0.1.0.dist-info/WHEEL
dtwsa-0.1.0.dist-info/licenses/LICENSE
dtwsa-0.1.0.dist-info/RECORD
