Metadata-Version: 2.3
Name: dtwsa
Version: 0.1.0
Summary: A package with a simple 1D-DTW implementation for sentence alignment.
Project-URL: Homepage, https://github.com/i4Ds/DTW-Sentence-Alignment
Project-URL: Issues, https://github.com/i4Ds/DTW-Sentence-Alignment/issues
Author-email: Vincenzo Timmel <vincenzo.timmel@fhnw.ch>
License-File: LICENSE
Classifier: License :: OSI Approved :: MIT License
Classifier: Operating System :: OS Independent
Classifier: Programming Language :: Python :: 3
Requires-Python: >=3.8
Requires-Dist: jiwer
Requires-Dist: matplotlib
Requires-Dist: numpy
